{"nodes": [{"id": "ui_shimmer_button", "label": "ShimmerButton", "file_type": "code", "source_file": "frontend/components/ui/shimmer-button.tsx", "source_location": null, "source_url": null, "captured_at": null, "author": null, "contributor": null}], "edges": [{"source": "ui_shimmer_button", "target": "lib_cn_cn", "relation": "calls", "confidence": "EXTRACTED", "confidence_score": 1.0, "source_file": "frontend/components/ui/shimmer-button.tsx", "source_location": null, "weight": 1.0}, {"source": "ui_shimmer_button", "target": "ui_shine_border", "relation": "semantically_similar_to", "confidence": "INFERRED", "confidence_score": 0.65, "source_file": "frontend/components/ui/shimmer-button.tsx", "source_location": null, "weight": 0.65}, {"source": "ui_interactive_hover_button", "target": "ui_shimmer_button", "relation": "conceptually_related_to", "confidence": "INFERRED", "confidence_score": 0.75, "source_file": "frontend/components/ui/shimmer-button.tsx", "source_location": null, "weight": 0.75}], "hyperedges": []}