{"nodes": [{"id": "blog_scraping_ao3_ffn", "label": "Scraping AO3 and FFN: A Tale of Two HTML Schemas", "file_type": "document", "source_file": "frontend/content/blog/scraping-ao3-and-ffn.mdx", "source_location": null, "source_url": null, "captured_at": "2026-05-10", "author": null, "contributor": null}, {"id": "blog_shared_schema_normalize", "label": "Shared-Schema Normalization with Source Tagging", "file_type": "rationale", "source_file": "frontend/content/blog/scraping-ao3-and-ffn.mdx", "source_location": null, "source_url": null, "captured_at": "2026-05-10", "author": null, "contributor": null}, {"id": "blog_ao3_scraper", "label": "AO3 Scraper (declarative, semantic HTML)", "file_type": "concept", "source_file": "frontend/content/blog/scraping-ao3-and-ffn.mdx", "source_location": null, "source_url": null, "captured_at": "2026-05-10", "author": null, "contributor": null}, {"id": "blog_ffn_scraper", "label": "FFN Scraper (regex-and-pray, messy HTML)", "file_type": "concept", "source_file": "frontend/content/blog/scraping-ao3-and-ffn.mdx", "source_location": null, "source_url": null, "captured_at": "2026-05-10", "author": null, "contributor": null}], "edges": [{"source": "blog_scraping_ao3_ffn", "target": "blog_ao3_scraper", "relation": "references", "confidence": "EXTRACTED", "confidence_score": 1.0, "source_file": "frontend/content/blog/scraping-ao3-and-ffn.mdx", "source_location": null, "weight": 1.0}, {"source": "blog_scraping_ao3_ffn", "target": "blog_ffn_scraper", "relation": "references", "confidence": "EXTRACTED", "confidence_score": 1.0, "source_file": "frontend/content/blog/scraping-ao3-and-ffn.mdx", "source_location": null, "weight": 1.0}, {"source": "blog_scraping_ao3_ffn", "target": "blog_shared_schema_normalize", "relation": "references", "confidence": "EXTRACTED", "confidence_score": 1.0, "source_file": "frontend/content/blog/scraping-ao3-and-ffn.mdx", "source_location": null, "weight": 1.0}, {"source": "blog_shared_schema_normalize", "target": "blog_ranker_blend_score", "relation": "conceptually_related_to", "confidence": "INFERRED", "confidence_score": 0.85, "source_file": "frontend/content/blog/scraping-ao3-and-ffn.mdx", "source_location": null, "weight": 1.0}, {"source": "blog_ao3_scraper", "target": "blog_ffn_scraper", "relation": "semantically_similar_to", "confidence": "INFERRED", "confidence_score": 0.75, "source_file": "frontend/content/blog/scraping-ao3-and-ffn.mdx", "source_location": null, "weight": 1.0}], "hyperedges": []}